merl/__init__.py
merl/merl.py
merl/merlkov.py
merl-0.2.0.dist-info/METADATA
merl-0.2.0.dist-info/WHEEL
merl-0.2.0.dist-info/top_level.txt
merl-0.2.0.dist-info/RECORD
