Metadata-Version: 2.4
Name: merl
Version: 0.2.0
Summary: A useless python library, aiming to emulate (not fetch/embed) the Merl experience found on the minecraft.net help page! Again, this is NOT the real Merl, but a really close copy! If you use it enough!
Home-page: https://github.com/O9Creeps/merl
Author: O9CreeperBoi
Author-email: example@example.com
License: MIT
Classifier: Development Status :: 4 - Beta
Classifier: Intended Audience :: Developers
Classifier: License :: Freeware
Classifier: Operating System :: OS Independent
Classifier: Programming Language :: Python :: 3.10
Classifier: Programming Language :: Python :: 3.11
Classifier: Programming Language :: Python :: 3.12
Classifier: Programming Language :: Python :: 3.13
Classifier: Programming Language :: Python :: 3.14
Classifier: Programming Language :: Python :: 3.15
Dynamic: author
Dynamic: author-email
Dynamic: classifier
Dynamic: home-page
Dynamic: license
Dynamic: summary
